{
  "kind": "singleType",
  "collectionName": "homes",
  "info": {
    "singularName": "home",
    "pluralName": "homes",
    "displayName": "Home"
  },
  "options": {
    "draftAndPublish": false
  },
  "attributes": {
    "seo": {
      "type": "component",
      "repeatable": false,
      "component": "sections.seo",
      "required": true
    },
    "blocks": {
      "type": "dynamiczone",
      "components": [
        "sections.hero",
        "sections.cta"
      ],
      "required": true
    }
  }
}
